plpacker/__init__.py
plpacker/cli.py
plpacker/config.py
plpacker/fileset.py
plpacker/packager.py
plpacker/pylambdapacker.py
plpacker/utils.py
plpacker/virtualenv.py
plpacker/conf/DEFAULT_CONFIG.yaml
plpacker/conf/logging.yaml
py_lambda_packer-0.1.0.dist-info/DESCRIPTION.rst
py_lambda_packer-0.1.0.dist-info/METADATA
py_lambda_packer-0.1.0.dist-info/RECORD
py_lambda_packer-0.1.0.dist-info/WHEEL
py_lambda_packer-0.1.0.dist-info/entry_points.txt
py_lambda_packer-0.1.0.dist-info/metadata.json
py_lambda_packer-0.1.0.dist-info/top_level.txt
