Metadata-Version: 2.0
Name: py-lambda-packer
Version: 0.1.0
Summary: Helps build AWS Lambda zip files for Python projects.
Home-page: https://github.com/digitalrounin/py-lambda-packer.git
Author: Pedro H.
Author-email: pedro@digitalrounin.com
License: MIT
Keywords: aws lambda
Platform: UNKNOWN
Classifier: Development Status :: 3 - Alpha
Classifier: Intended Audience :: Developers
Classifier: Intended Audience :: System Administrators
Classifier: Topic :: Software Development :: Build Tools
Classifier: License :: OSI Approved :: MIT License
Classifier: Programming Language :: Python :: 2
Classifier: Programming Language :: Python :: 2.7
Classifier: Programming Language :: Python :: 3
Classifier: Programming Language :: Python :: 3.6
Requires-Dist: PyYAML (>=3.12)
Requires-Dist: colorlog (>=2.10.0)
Requires-Dist: future (>=0.16.0)
